LICENSE
MANIFEST.in
README.md
requirements.txt
setup.cfg
setup.py
openre/__init__.py
openre/data_types.py
openre/errors.py
openre/helpers.py
openre/layer.py
openre/metadata.py
openre/neurons.py
openre/synapses.py
openre/templates.py
openre/vector.py
openre.egg-info/PKG-INFO
openre.egg-info/SOURCES.txt
openre.egg-info/dependency_links.txt
openre.egg-info/requires.txt
openre.egg-info/top_level.txt
openre/agent/__init__.py
openre/agent/args.py
openre/agent/decorators.py
openre/agent/event.py
openre/agent/helpers.py
openre/agent/broker/__init__.py
openre/agent/broker/args.py
openre/agent/broker/broker.py
openre/agent/client/__init__.py
openre/agent/client/args.py
openre/agent/client/client.py
openre/agent/client/decorators.py
openre/agent/client/helpers.py
openre/agent/client/action/__init__.py
openre/agent/client/action/config.py
openre/agent/client/action/deploy.py
openre/agent/client/action/run.py
openre/agent/client/action/tests.py
openre/agent/domain/__init__.py
openre/agent/domain/args.py
openre/agent/domain/decorators.py
openre/agent/domain/domain.py
openre/agent/domain/action/__init__.py
openre/agent/domain/action/config.py
openre/agent/domain/action/deploy.py
openre/agent/domain/action/run.py
openre/agent/domain/action/utils.py
openre/agent/proxy/__init__.py
openre/agent/proxy/args.py
openre/agent/proxy/proxy.py
openre/agent/server/__init__.py
openre/agent/server/args.py
openre/agent/server/decorators.py
openre/agent/server/helpers.py
openre/agent/server/server.py
openre/agent/server/state.py
openre/agent/server/action/__init__.py
openre/agent/server/action/broker.py
openre/agent/server/action/domain.py
openre/agent/server/action/proxy.py
openre/agent/server/action/state.py
openre/agent/server/action/utils.py
openre/bin/openre-agent
openre/bin/openre-broker
openre/bin/openre-domain
openre/bin/openre-proxy
openre/bin/openre-server
openre/bin/openrectl
openre/device/__init__.py
openre/device/abstract.py
openre/device/dummy.py
openre/device/opencl.py
openre/domain/__init__.py
openre/domain/base.py
openre/domain/local.py
openre/domain/packets.py
openre/domain/remote.py
openre/index/__init__.py
