Metadata-Version: 1.1
Name: openre
Version: 0.0.2
Summary: OpenRE - self-learning neural network
Home-page: https://github.com/openre/openre
Author: Dmitriy Boyarshinov
Author-email: dmitriy.boyarshinov@gmail.com
License: The MIT License
